{
  "descriptionHash": "5EE21FE8F2D9F22714EF30CBD2D795A38EA6ACD2D52E4E32A3F93BB4760E17E1A25A9BA94F55B32B89FCDF8DCF6A4C9BA34DD4974467225B628BDDCDFF00AD94",
  "descriptionLocation": "../../DigitalOcean-public.v2.yaml",
  "lockFileVersion": "1.0.0",
  "kiotaVersion": "1.28.0",
  "clientClassName": "DigitalOceanClient",
  "typeAccessModifier": "Public",
  "clientNamespaceName": "ApiSdk",
  "language": "TypeScript",
  "usesBackingStore": false,
  "excludeBackwardCompatible": false,
  "includeAdditionalData": true,
  "disableSSLValidation": false,
  "serializers": [
    "Microsoft.Kiota.Serialization.Json.JsonSerializationWriterFactory",
    "Microsoft.Kiota.Serialization.Text.TextSerializationWriterFactory",
    "Microsoft.Kiota.Serialization.Form.FormSerializationWriterFactory",
    "Microsoft.Kiota.Serialization.Multipart.MultipartSerializationWriterFactory"
  ],
  "deserializers": [
    "Microsoft.Kiota.Serialization.Json.JsonParseNodeFactory",
    "Microsoft.Kiota.Serialization.Text.TextParseNodeFactory",
    "Microsoft.Kiota.Serialization.Form.FormParseNodeFactory"
  ],
  "structuredMimeTypes": [
    "application/json",
    "text/plain;q=0.9",
    "application/x-www-form-urlencoded;q=0.2",
    "multipart/form-data;q=0.1"
  ],
  "includePatterns": [],
  "excludePatterns": [],
  "disabledValidationRules": []
}